setup.py
iatisegmenter/__init__.py
iatisegmenter/segment.py
iatisegmenter.egg-info/PKG-INFO
iatisegmenter.egg-info/SOURCES.txt
iatisegmenter.egg-info/dependency_links.txt
iatisegmenter.egg-info/requires.txt
iatisegmenter.egg-info/top_level.txt