Metadata-Version: 1.0
Name: iatisegmenter
Version: 0.1
Summary: Python library for segmenting IATI-XML data to one country or region
Home-page: UNKNOWN
Author: Mark Brough
Author-email: mark.brough@publishwhatyoufund.org
License: GNU Affero General Public License v3.0
Platform: UNKNOWN
